{
  "orderId": "ALPHA_1764276441038",
  "name": "ALPHA (CASH CASCADE)",
  "objective": "Maximize cash velocity. Close low-friction deals immediately to fund operations while advancing enterprise contracts.",
  "initiatedAt": "2025-11-27T20:47:21.038Z",
  "status": "INITIATED",
  "phases": [
    {
      "phase": 1,
      "name": "LIQUIDITY SPRINT",
      "target": "24 Hours",
      "status": "ACTIVE",
      "startedAt": "2025-11-27T20:47:21.038Z",
      "successMetric": "$12,000 processed",
      "totalValue": 12000,
      "deals": [
        {
          "id": "DEAL-006",
          "description": "Membership upgrade opportunity - Premium tier conversion",
          "estimatedValue": 4500,
          "phase": 1,
          "priority": "P1",
          "status": "IN_PROGRESS",
          "deadline": "2025-11-28T20:47:21.038Z",
          "tactics": [
            "Issue \"Buy Now\" link immediately",
            "Send final invoice with scarcity messaging",
            "Use deadline: \"Pricing locks at midnight\"",
            "No nurturing - direct close only"
          ]
        },
        {
          "id": "DEAL-004",
          "description": "Paid strategy session - implementation planning",
          "estimatedValue": 7500,
          "phase": 1,
          "priority": "P1",
          "status": "IN_PROGRESS",
          "deadline": "2025-11-28T20:47:21.038Z",
          "tactics": [
            "Issue \"Buy Now\" link immediately",
            "Send final invoice with scarcity messaging",
            "Use deadline: \"Strategy session slots filling fast\"",
            "No nurturing - direct close only"
          ]
        }
      ]
    },
    {
      "phase": 2,
      "name": "URGENCY",
      "target": "48 Hours",
      "status": "PENDING",
      "successMetric": "$22,000 closed",
      "totalValue": 82000,
      "deals": [
        {
          "id": "DEAL-007",
          "description": "Paid audit request from diagnostics company",
          "estimatedValue": 22000,
          "phase": 2,
          "priority": "P1",
          "status": "PENDING",
          "deadline": "2025-11-29T20:47:21.038Z",
          "tactics": [
            "Leverage regulatory deadline pressure",
            "Message: \"Audit schedule is filling. Confirm by [Date] to secure Q4 delivery.\"",
            "Emphasize compliance timeline urgency",
            "Offer priority scheduling for immediate commitment"
          ]
        },
        {
          "id": "DEAL-002",
          "description": "Finalize proposal for BioTech Solutions regulatory audit package",
          "estimatedValue": 42000,
          "phase": 2,
          "priority": "P1",
          "status": "PENDING",
          "deadline": "2025-11-29T20:47:21.185Z",
          "tactics": [
            "Finalize proposal immediately",
            "Send with urgency messaging",
            "Follow up within 24h"
          ]
        },
        {
          "id": "DEAL-005",
          "description": "Quote request from clinical trial sponsor for evidence pack",
          "estimatedValue": 18000,
          "phase": 2,
          "priority": "P1",
          "status": "PENDING",
          "deadline": "2025-11-29T20:47:21.279Z",
          "tactics": [
            "Finalize proposal immediately",
            "Send with urgency messaging",
            "Follow up within 24h"
          ]
        }
      ]
    },
    {
      "phase": 3,
      "name": "THE ANCHORS",
      "target": "7 Days",
      "status": "PENDING",
      "successMetric": "$241,000 contracted",
      "totalValue": 241000,
      "deals": [
        {
          "id": "DEAL-003",
          "description": "Contract negotiation MedDevice Inc - 3yr SaaS subscription",
          "estimatedValue": 156000,
          "phase": 3,
          "priority": "P1",
          "status": "PENDING",
          "deadline": "2025-12-04T20:47:21.038Z",
          "signatureBlocker": "PENDING IDENTIFICATION",
          "blockerRemovalTactic": "Map the decision chain. Identify exactly who or what is stopping the signature today.",
          "tactics": [
            "Identify signature blocker (Legal? Budget? Champion absence?)",
            "Generate specific removal tactic for that blocker",
            "Escalate to executive sponsor if needed",
            "Offer contract flexibility to remove friction"
          ]
        },
        {
          "id": "DEAL-001",
          "description": "Close enterprise deal PharmaCorp - annual compliance platform contract",
          "estimatedValue": 85000,
          "phase": 3,
          "priority": "P1",
          "status": "PENDING",
          "deadline": "2025-12-04T20:47:21.038Z",
          "signatureBlocker": "PENDING IDENTIFICATION",
          "blockerRemovalTactic": "Map the decision chain. Identify exactly who or what is stopping the signature today.",
          "tactics": [
            "Identify signature blocker (Legal? Budget? Champion absence?)",
            "Generate specific removal tactic for that blocker",
            "Escalate to executive sponsor if needed",
            "Offer contract flexibility to remove friction"
          ]
        }
      ]
    }
  ],
  "corrections": [
    {
      "dealId": "DEAL-002",
      "from": "P2 (Paused)",
      "to": "P1 (Critical)",
      "reason": "Active proposals are revenue-generating activities",
      "correctedAt": "2025-11-27T20:47:21.185Z"
    },
    {
      "dealId": "DEAL-005",
      "from": "P2 (Paused)",
      "to": "P1 (Critical)",
      "reason": "Active proposals are revenue-generating activities",
      "correctedAt": "2025-11-27T20:47:21.279Z"
    }
  ],
  "closureReport": {
    "phase1Closed": 0,
    "phase2Closed": 0,
    "phase3Closed": 0,
    "totalClosed": 0,
    "totalValue": 0
  }
}